kornia/__init__.py
kornia/config.py
kornia/constants.py
kornia/py.typed
kornia/augmentation/__init__.py
kornia/augmentation/base.py
kornia/augmentation/_2d/__init__.py
kornia/augmentation/_2d/base.py
kornia/augmentation/_2d/geometric/__init__.py
kornia/augmentation/_2d/geometric/affine.py
kornia/augmentation/_2d/geometric/base.py
kornia/augmentation/_2d/geometric/center_crop.py
kornia/augmentation/_2d/geometric/crop.py
kornia/augmentation/_2d/geometric/elastic_transform.py
kornia/augmentation/_2d/geometric/fisheye.py
kornia/augmentation/_2d/geometric/horizontal_flip.py
kornia/augmentation/_2d/geometric/pad.py
kornia/augmentation/_2d/geometric/perspective.py
kornia/augmentation/_2d/geometric/resize.py
kornia/augmentation/_2d/geometric/resized_crop.py
kornia/augmentation/_2d/geometric/rotation.py
kornia/augmentation/_2d/geometric/shear.py
kornia/augmentation/_2d/geometric/thin_plate_spline.py
kornia/augmentation/_2d/geometric/translate.py
kornia/augmentation/_2d/geometric/vertical_flip.py
kornia/augmentation/_2d/intensity/__init__.py
kornia/augmentation/_2d/intensity/auto_contrast.py
kornia/augmentation/_2d/intensity/base.py
kornia/augmentation/_2d/intensity/box_blur.py
kornia/augmentation/_2d/intensity/brightness.py
kornia/augmentation/_2d/intensity/channel_dropout.py
kornia/augmentation/_2d/intensity/channel_shuffle.py
kornia/augmentation/_2d/intensity/clahe.py
kornia/augmentation/_2d/intensity/color_jiggle.py
kornia/augmentation/_2d/intensity/color_jitter.py
kornia/augmentation/_2d/intensity/contrast.py
kornia/augmentation/_2d/intensity/denormalize.py
kornia/augmentation/_2d/intensity/dissolving.py
kornia/augmentation/_2d/intensity/equalize.py
kornia/augmentation/_2d/intensity/erasing.py
kornia/augmentation/_2d/intensity/gamma.py
kornia/augmentation/_2d/intensity/gaussian_blur.py
kornia/augmentation/_2d/intensity/gaussian_illumination.py
kornia/augmentation/_2d/intensity/gaussian_noise.py
kornia/augmentation/_2d/intensity/grayscale.py
kornia-0.8.0.dist-info/LICENSE
kornia-0.8.0.dist-info/METADATA
kornia-0.8.0.dist-info/WHEEL
kornia-0.8.0.dist-info/top_level.txt
kornia-0.8.0.dist-info/zip-safe
kornia-0.8.0.dist-info/RECORD
