Metadata-Version: 2.2
Name: kornia
Version: 0.8.0
Summary: Open Source Differentiable Computer Vision Library for PyTorch
Author-email: Edgar Riba <edgar@kornia.org>
License: Apache-2.0
Project-URL: Bug Tracker, https://github.com/kornia/kornia/issues
Project-URL: Documentation, https://kornia.readthedocs.io/en/latest
Project-URL: Download, https://github.com/kornia/kornia
Project-URL: Issues, https://github.com/kornia/kornia/issues
Project-URL: Homepage, https://kornia.github.io/
Project-URL: Source Code, https://github.com/kornia/kornia
Keywords: computer vision,deep learning,pytorch
Classifier: Development Status :: 4 - Beta
Classifier: Environment :: Console
Classifier: Environment :: GPU
Classifier: Intended Audience :: Developers
Classifier: Intended Audience :: Education
Classifier: Intended Audience :: Information Technology
Classifier: Intended Audience :: Science/Research
Classifier: License :: OSI Approved :: Apache Software License
Classifier: Natural Language :: English
Classifier: Operating System :: OS Independent
Classifier: Programming Language :: Python :: 3 :: Only
Classifier: Programming Language :: Python :: 3.9
Classifier: Programming Language :: Python :: 3.10
Classifier: Programming Language :: Python :: 3.11
Classifier: Programming Language :: Python :: 3.12
Classifier: Topic :: Scientific/Engineering :: Artificial Intelligence
Classifier: Topic :: Scientific/Engineering :: Image Processing
Classifier: Topic :: Software Development :: Libraries
Requires-Python: >=3.9
License-File: LICENSE
Requires-Dist: kornia_rs>=0.1.0
Requires-Dist: packaging
Requires-Dist: torch>=1.9.1
Provides-Extra: dev
Requires-Dist: accelerate; extra == "dev"
Requires-Dist: coverage; extra == "dev"
Requires-Dist: diffusers; extra == "dev"
Requires-Dist: ivy>=1.0.0.0; extra == "dev"
Requires-Dist: mypy; extra == "dev"
Requires-Dist: numpy<3; extra == "dev"
Requires-Dist: onnx; extra == "dev"
Requires-Dist: onnxruntime; extra == "dev"
Requires-Dist: pillow; extra == "dev"
Requires-Dist: pre-commit>=2; extra == "dev"
Requires-Dist: pytest==8.3.4; extra == "dev"
Requires-Dist: pytest-timeout; extra == "dev"
Requires-Dist: requests; extra == "dev"
Requires-Dist: setuptools>=61.2; extra == "dev"
Requires-Dist: transformers; extra == "dev"
Requires-Dist: types-requests; extra == "dev"
Provides-Extra: docs
Requires-Dist: furo; extra == "docs"
Requires-Dist: ivy>=1.0.0.0; extra == "docs"
Requires-Dist: kornia_moons; extra == "docs"
Requires-Dist: matplotlib; extra == "docs"
Requires-Dist: onnx; extra == "docs"
Requires-Dist: onnxruntime; extra == "docs"
Requires-Dist: opencv-python; extra == "docs"
Requires-Dist: PyYAML>=5.1; extra == "docs"
Requires-Dist: sphinx; extra == "docs"
Requires-Dist: sphinx-autodoc-defaultargs; extra == "docs"
Requires-Dist: sphinx-autodoc-typehints; extra == "docs"
Requires-Dist: sphinx-copybutton>=0.3; extra == "docs"
Requires-Dist: sphinx-design; extra == "docs"
Requires-Dist: sphinx-notfound-page; extra == "docs"
Requires-Dist: sphinxcontrib-bibtex; extra == "docs"
Requires-Dist: sphinxcontrib-gtagjs; extra == "docs"
Requires-Dist: sphinxcontrib-youtube; extra == "docs"
Provides-Extra: x
Requires-Dist: accelerate; extra == "x"
Requires-Dist: onnxruntime-gpu>=1.16; sys_platform != "darwin" and extra == "x"
